solman/__init__.py
solman/build.py
solman/latex.py
solman/soln.py
solman/templates/template.tex
tests/__init__.py
tests/test_latex.py
tests/test_soln.py
solman-0.0.2.dist-info/LICENSE
solman-0.0.2.dist-info/METADATA
solman-0.0.2.dist-info/WHEEL
solman-0.0.2.dist-info/top_level.txt
solman-0.0.2.dist-info/RECORD
