Metadata-Version: 2.1
Name: solman
Version: 0.0.2
Summary: Solutions manual writing utility in Python.
Home-page: http://github.com/JWKennington/solman
Author: James W. Kennington
Author-email: jameswkennington@gmail.com
License: MIT
Platform: UNKNOWN
